{
  "attributes": {
    "address": {
      "description": "Address",
      "disable_correlation": false,
      "misp-attribute": "text",
      "multiple": true,
      "ui-priority": 0
    },
    "alephUrl": {
      "description": "Aleph URL",
      "disable_correlation": false,
      "misp-attribute": "url",
      "multiple": true,
      "ui-priority": 0
    },
    "alias": {
      "description": "Other name",
      "disable_correlation": false,
      "misp-attribute": "text",
      "multiple": true,
      "ui-priority": 0
    },
    "birthDate": {
      "description": "Birth date",
      "disable_correlation": false,
      "misp-attribute": "text",
      "multiple": true,
      "ui-priority": 1
    },
    "birthPlace": {
      "description": "Place of birth",
      "disable_correlation": true,
      "misp-attribute": "text",
      "multiple": true,
      "ui-priority": 0
    },
    "bvdId": {
      "description": "Bureau van Dijk ID",
      "disable_correlation": false,
      "misp-attribute": "text",
      "multiple": true,
      "ui-priority": 0
    },
    "classification": {
      "description": "Classification",
      "disable_correlation": true,
      "misp-attribute": "text",
      "multiple": true,
      "ui-priority": 0
    },
    "country": {
      "description": "Country",
      "disable_correlation": false,
      "misp-attribute": "text",
      "multiple": true,
      "ui-priority": 1
    },
    "deathDate": {
      "description": "Death date",
      "disable_correlation": false,
      "misp-attribute": "text",
      "multiple": true,
      "ui-priority": 0
    },
    "description": {
      "description": "Description",
      "disable_correlation": true,
      "misp-attribute": "text",
      "multiple": true,
      "ui-priority": 0
    },
    "dissolutionDate": {
      "description": "The date the legal entity was dissolved, if applicable",
      "disable_correlation": false,
      "misp-attribute": "text",
      "multiple": true,
      "ui-priority": 0
    },
    "dunsCode": {
      "description": "Dun & Bradstreet identifier",
      "disable_correlation": false,
      "misp-attribute": "text",
      "multiple": true,
      "ui-priority": 0
    },
    "email": {
      "description": "Email address",
      "disable_correlation": false,
      "misp-attribute": "email-src",
      "multiple": true,
      "ui-priority": 0
    },
    "fatherName": {
      "description": "Patronymic",
      "disable_correlation": true,
      "misp-attribute": "text",
      "multiple": true,
      "ui-priority": 0
    },
    "firstName": {
      "description": "First name",
      "disable_correlation": true,
      "misp-attribute": "text",
      "multiple": true,
      "ui-priority": 0
    },
    "gender": {
      "description": "Gender",
      "disable_correlation": true,
      "misp-attribute": "text",
      "multiple": true,
      "ui-priority": 0
    },
    "icijId": {
      "description": "ID according to International Consortium for Investigative Journalists",
      "disable_correlation": true,
      "misp-attribute": "text",
      "multiple": true,
      "ui-priority": 0
    },
    "idNumber": {
      "description": "ID number of any applicable ID",
      "disable_correlation": false,
      "misp-attribute": "text",
      "multiple": true,
      "ui-priority": 0
    },
    "incorporationDate": {
      "description": "The date the legal entity was incorporated",
      "disable_correlation": false,
      "misp-attribute": "text",
      "multiple": true,
      "ui-priority": 0
    },
    "indexText": {
      "description": "Index text",
      "disable_correlation": true,
      "misp-attribute": "text",
      "multiple": true,
      "ui-priority": 0
    },
    "indexUpdatedAt": {
      "description": "Index updated at",
      "disable_correlation": false,
      "misp-attribute": "text",
      "multiple": true,
      "ui-priority": 0
    },
    "innCode": {
      "description": "Russian company ID",
      "disable_correlation": false,
      "misp-attribute": "text",
      "multiple": true,
      "ui-priority": 0
    },
    "jurisdiction": {
      "description": "Country or region in which this entity operates",
      "disable_correlation": false,
      "misp-attribute": "text",
      "multiple": true,
      "ui-priority": 0
    },
    "keywords": {
      "description": "Keywords",
      "disable_correlation": true,
      "misp-attribute": "text",
      "multiple": true,
      "ui-priority": 0
    },
    "lastName": {
      "description": "Last name",
      "disable_correlation": true,
      "misp-attribute": "text",
      "multiple": true,
      "ui-priority": 0
    },
    "legalForm": {
      "description": "Legal form",
      "disable_correlation": true,
      "misp-attribute": "text",
      "multiple": true,
      "ui-priority": 1
    },
    "mainCountry": {
      "description": "Primary country of this entity",
      "disable_correlation": false,
      "misp-attribute": "text",
      "multiple": true,
      "ui-priority": 0
    },
    "middleName": {
      "description": "Middle name",
      "disable_correlation": true,
      "misp-attribute": "text",
      "multiple": true,
      "ui-priority": 0
    },
    "modifiedAt": {
      "description": "Modified on",
      "disable_correlation": false,
      "misp-attribute": "text",
      "multiple": true,
      "ui-priority": 0
    },
    "motherName": {
      "description": "Matronymic",
      "disable_correlation": true,
      "misp-attribute": "text",
      "multiple": true,
      "ui-priority": 0
    },
    "name": {
      "description": "Name",
      "disable_correlation": false,
      "misp-attribute": "text",
      "multiple": true,
      "ui-priority": 1
    },
    "nationality": {
      "description": "Nationality",
      "disable_correlation": false,
      "misp-attribute": "text",
      "multiple": true,
      "ui-priority": 1
    },
    "notes": {
      "description": "Notes",
      "disable_correlation": true,
      "misp-attribute": "text",
      "multiple": true,
      "ui-priority": 0
    },
    "okpoCode": {
      "description": "Russian industry classifier",
      "disable_correlation": false,
      "misp-attribute": "text",
      "multiple": true,
      "ui-priority": 0
    },
    "opencorporatesUrl": {
      "description": "OpenCorporates URL",
      "disable_correlation": false,
      "misp-attribute": "url",
      "multiple": true,
      "ui-priority": 0
    },
    "passportNumber": {
      "description": "Passport",
      "disable_correlation": false,
      "misp-attribute": "text",
      "multiple": true,
      "ui-priority": 0
    },
    "phone": {
      "description": "Phone number",
      "disable_correlation": false,
      "misp-attribute": "phone-number",
      "multiple": true,
      "ui-priority": 0
    },
    "position": {
      "description": "Position",
      "disable_correlation": true,
      "misp-attribute": "text",
      "multiple": true,
      "ui-priority": 0
    },
    "previousName": {
      "description": "Previous name",
      "disable_correlation": false,
      "misp-attribute": "text",
      "multiple": true,
      "ui-priority": 0
    },
    "program": {
      "description": "Program",
      "disable_correlation": true,
      "misp-attribute": "text",
      "multiple": true,
      "ui-priority": 0
    },
    "publisher": {
      "description": "Publishing source",
      "disable_correlation": true,
      "misp-attribute": "text",
      "multiple": true,
      "ui-priority": 0
    },
    "publisherUrl": {
      "description": "Publishing source URL",
      "disable_correlation": false,
      "misp-attribute": "url",
      "multiple": true,
      "ui-priority": 0
    },
    "registrationNumber": {
      "description": "Company registration number",
      "disable_correlation": false,
      "misp-attribute": "text",
      "multiple": true,
      "ui-priority": 0
    },
    "retrievedAt": {
      "description": "Retrieved on",
      "disable_correlation": false,
      "misp-attribute": "text",
      "multiple": true,
      "ui-priority": 0
    },
    "secondName": {
      "description": "Second name",
      "disable_correlation": true,
      "misp-attribute": "text",
      "multiple": true,
      "ui-priority": 0
    },
    "sector": {
      "description": "Sector",
      "disable_correlation": true,
      "misp-attribute": "text",
      "multiple": true,
      "ui-priority": 0
    },
    "sourceUrl": {
      "description": "Source link",
      "disable_correlation": false,
      "misp-attribute": "url",
      "multiple": true,
      "ui-priority": 0
    },
    "status": {
      "description": "Status",
      "disable_correlation": true,
      "misp-attribute": "text",
      "multiple": true,
      "ui-priority": 0
    },
    "summary": {
      "description": "Summary",
      "disable_correlation": true,
      "misp-attribute": "text",
      "multiple": true,
      "ui-priority": 0
    },
    "swiftBic": {
      "description": "Bank identifier code",
      "disable_correlation": false,
      "misp-attribute": "text",
      "multiple": true,
      "ui-priority": 0
    },
    "taxNumber": {
      "description": "Tax identification number",
      "disable_correlation": false,
      "misp-attribute": "text",
      "multiple": true,
      "ui-priority": 0
    },
    "taxStatus": {
      "description": "Tax status",
      "disable_correlation": true,
      "misp-attribute": "text",
      "multiple": true,
      "ui-priority": 0
    },
    "title": {
      "description": "Title",
      "disable_correlation": true,
      "misp-attribute": "text",
      "multiple": true,
      "ui-priority": 0
    },
    "topics": {
      "description": "Topics",
      "disable_correlation": false,
      "misp-attribute": "text",
      "multiple": true,
      "ui-priority": 0
    },
    "vatCode": {
      "description": "(EU) VAT number",
      "disable_correlation": false,
      "misp-attribute": "text",
      "multiple": true,
      "ui-priority": 0
    },
    "weakAlias": {
      "description": "Weak alias",
      "disable_correlation": true,
      "misp-attribute": "text",
      "multiple": true,
      "ui-priority": 0
    },
    "website": {
      "description": "Website address",
      "disable_correlation": false,
      "misp-attribute": "url",
      "multiple": true,
      "ui-priority": 0
    },
    "wikidataId": {
      "description": "Wikidata ID",
      "disable_correlation": false,
      "misp-attribute": "text",
      "multiple": true,
      "ui-priority": 0
    },
    "wikipediaUrl": {
      "description": "Wikipedia Article",
      "disable_correlation": false,
      "misp-attribute": "url",
      "multiple": true,
      "ui-priority": 0
    }
  },
  "description": "An individual",
  "meta-category": "followthemoney",
  "name": "ftm-Person",
  "required": [
    "name"
  ],
  "uuid": "070e1c5b-7f5a-4322-81ff-9d684172fe36",
  "version": 1
}