{
  "attributes": {
    "Directory": {
      "description": "Directory",
      "disable_correlation": true,
      "misp-attribute": "text",
      "ui-priority": 0
    },
    "FileName": {
      "description": "File Name",
      "disable_correlation": true,
      "misp-attribute": "text",
      "ui-priority": 0
    },
    "FilePermissions": {
      "description": "File Permissions",
      "disable_correlation": true,
      "misp-attribute": "text",
      "ui-priority": 0
    },
    "FileSize": {
      "description": "File Size",
      "disable_correlation": true,
      "misp-attribute": "text",
      "ui-priority": 0
    },
    "FileType": {
      "description": "File Type",
      "disable_correlation": true,
      "misp-attribute": "text",
      "ui-priority": 0
    },
    "FileTypeExtension": {
      "description": "File Type Extension",
      "disable_correlation": true,
      "misp-attribute": "text",
      "ui-priority": 0
    },
    "MIMEType": {
      "description": "MIME Type",
      "disable_correlation": true,
      "misp-attribute": "mime-type",
      "ui-priority": 0
    }
  },
  "description": "Object describing file metadata.",
  "meta-category": "file",
  "name": "audio-x-wav-image",
  "requiredOneof": [
    "FileName",
    "Directory",
    "FileSize",
    "FilePermissions",
    "FileType",
    "FileTypeExtension",
    "MIMEType"
  ],
  "uuid": "d22c0b82-40d9-47d0-aa1e-89d7215ec627",
  "version": 1
}
