{
    "attributes": {
        "Composite-Duration": {
            "description": "Duration",
            "disable_correlation": true,
            "misp-attribute": "text",
            "ui-priority": 0
        },
        "ExifTool-ExifToolVersion": {
            "description": "ExifTool Version Number",
            "disable_correlation": true,
            "misp-attribute": "text",
            "ui-priority": 0
        },
        "FLAC-BitsPerSample": {
            "description": "Bits Per Sample",
            "disable_correlation": true,
            "misp-attribute": "text",
            "ui-priority": 0
        },
        "FLAC-BlockSizeMax": {
            "description": "Block Size Max",
            "disable_correlation": true,
            "misp-attribute": "text",
            "ui-priority": 0
        },
        "FLAC-BlockSizeMin": {
            "description": "Block Size Min",
            "disable_correlation": true,
            "misp-attribute": "text",
            "ui-priority": 0
        },
        "FLAC-Channels": {
            "description": "Channels",
            "disable_correlation": true,
            "misp-attribute": "text",
            "ui-priority": 0
        },
        "FLAC-FrameSizeMax": {
            "description": "Frame Size Max",
            "disable_correlation": true,
            "misp-attribute": "text",
            "ui-priority": 0
        },
        "FLAC-FrameSizeMin": {
            "description": "Frame Size Min",
            "disable_correlation": true,
            "misp-attribute": "text",
            "ui-priority": 0
        },
        "FLAC-MD5Signature": {
            "description": "MD5 Signature",
            "disable_correlation": true,
            "misp-attribute": "text",
            "ui-priority": 0
        },
        "FLAC-Picture": {
            "description": "Picture",
            "disable_correlation": true,
            "misp-attribute": "text",
            "ui-priority": 0
        },
        "FLAC-PictureBitsPerPixel": {
            "description": "Picture Bits Per Pixel",
            "disable_correlation": true,
            "misp-attribute": "text",
            "ui-priority": 0
        },
        "FLAC-PictureDescription": {
            "description": "Picture Description",
            "disable_correlation": true,
            "misp-attribute": "text",
            "ui-priority": 0
        },
        "FLAC-PictureHeight": {
            "description": "Picture Height",
            "disable_correlation": true,
            "misp-attribute": "text",
            "ui-priority": 0
        },
        "FLAC-PictureIndexedColors": {
            "description": "Picture Indexed Colors",
            "disable_correlation": true,
            "misp-attribute": "text",
            "ui-priority": 0
        },
        "FLAC-PictureLength": {
            "description": "Picture Length",
            "disable_correlation": true,
            "misp-attribute": "text",
            "ui-priority": 0
        },
        "FLAC-PictureMIMEType": {
            "description": "Picture MIME Type",
            "disable_correlation": true,
            "misp-attribute": "mime-type",
            "ui-priority": 0
        },
        "FLAC-PictureType": {
            "description": "Picture Type",
            "disable_correlation": true,
            "misp-attribute": "text",
            "ui-priority": 0
        },
        "FLAC-PictureWidth": {
            "description": "Picture Width",
            "disable_correlation": true,
            "misp-attribute": "text",
            "ui-priority": 0
        },
        "FLAC-SampleRate": {
            "description": "Sample Rate",
            "disable_correlation": true,
            "misp-attribute": "text",
            "ui-priority": 0
        },
        "FLAC-TotalSamples": {
            "description": "Total Samples",
            "disable_correlation": true,
            "misp-attribute": "text",
            "ui-priority": 0
        },
        "File-Directory": {
            "description": "Directory",
            "disable_correlation": true,
            "misp-attribute": "text",
            "ui-priority": 0
        },
        "File-FileAccessDate": {
            "description": "File Access Date/Time",
            "disable_correlation": true,
            "misp-attribute": "datetime",
            "ui-priority": 0
        },
        "File-FileInodeChangeDate": {
            "description": "File Inode Change Date/Time",
            "disable_correlation": true,
            "misp-attribute": "datetime",
            "ui-priority": 0
        },
        "File-FileModifyDate": {
            "description": "File Modification Date/Time",
            "disable_correlation": true,
            "misp-attribute": "datetime",
            "ui-priority": 0
        },
        "File-FileName": {
            "description": "File Name",
            "disable_correlation": true,
            "misp-attribute": "text",
            "ui-priority": 0
        },
        "File-FilePermissions": {
            "description": "File Permissions",
            "disable_correlation": true,
            "misp-attribute": "text",
            "ui-priority": 0
        },
        "File-FileSize": {
            "description": "File Size",
            "disable_correlation": true,
            "misp-attribute": "text",
            "ui-priority": 0
        },
        "File-FileType": {
            "description": "File Type",
            "disable_correlation": true,
            "misp-attribute": "text",
            "ui-priority": 0
        },
        "File-FileTypeExtension": {
            "description": "File Type Extension",
            "disable_correlation": true,
            "misp-attribute": "text",
            "ui-priority": 0
        },
        "File-MIMEType": {
            "description": "MIME Type",
            "disable_correlation": true,
            "misp-attribute": "mime-type",
            "ui-priority": 0
        },
        "Opus-AudioChannels": {
            "description": "Audio Channels",
            "disable_correlation": true,
            "misp-attribute": "text",
            "ui-priority": 0
        },
        "Opus-OpusVersion": {
            "description": "Opus Version",
            "disable_correlation": true,
            "misp-attribute": "text",
            "ui-priority": 0
        },
        "Opus-OutputGain": {
            "description": "Output Gain",
            "disable_correlation": true,
            "misp-attribute": "text",
            "ui-priority": 0
        },
        "Opus-SampleRate": {
            "description": "Sample Rate",
            "disable_correlation": true,
            "misp-attribute": "text",
            "ui-priority": 0
        },
        "SourceFile": {
            "description": "Source File Path",
            "disable_correlation": true,
            "misp-attribute": "text",
            "ui-priority": 0
        },
        "Vorbis-Album": {
            "description": "Album",
            "disable_correlation": true,
            "misp-attribute": "text",
            "ui-priority": 0
        },
        "Vorbis-Artist": {
            "description": "Artist",
            "disable_correlation": true,
            "misp-attribute": "text",
            "ui-priority": 0
        },
        "Vorbis-AudioChannels": {
            "description": "Audio Channels",
            "disable_correlation": true,
            "misp-attribute": "text",
            "ui-priority": 0
        },
        "Vorbis-Comment": {
            "description": "Comment",
            "disable_correlation": true,
            "misp-attribute": "text",
            "ui-priority": 0
        },
        "Vorbis-CoverArt": {
            "description": "Cover Art",
            "disable_correlation": true,
            "misp-attribute": "text",
            "ui-priority": 0
        },
        "Vorbis-CoverArtMIMEType": {
            "description": "Cover Art MIME Type",
            "disable_correlation": true,
            "misp-attribute": "mime-type",
            "ui-priority": 0
        },
        "Vorbis-Date": {
            "description": "Date",
            "disable_correlation": true,
            "misp-attribute": "text",
            "ui-priority": 0
        },
        "Vorbis-Encoder": {
            "description": "Encoder",
            "disable_correlation": true,
            "misp-attribute": "text",
            "ui-priority": 0
        },
        "Vorbis-Genre": {
            "description": "Genre",
            "disable_correlation": true,
            "misp-attribute": "text",
            "ui-priority": 0
        },
        "Vorbis-MediajukeboxDate": {
            "description": "Mediajukebox Date",
            "disable_correlation": true,
            "misp-attribute": "text",
            "ui-priority": 0
        },
        "Vorbis-MediajukeboxToolName": {
            "description": "Mediajukebox Tool Name",
            "disable_correlation": true,
            "misp-attribute": "text",
            "ui-priority": 0
        },
        "Vorbis-MediajukeboxToolVersion": {
            "description": "Mediajukebox Tool Version",
            "disable_correlation": true,
            "misp-attribute": "datetime",
            "ui-priority": 0
        },
        "Vorbis-NominalBitrate": {
            "description": "Nominal Bitrate",
            "disable_correlation": true,
            "misp-attribute": "text",
            "ui-priority": 0
        },
        "Vorbis-SampleRate": {
            "description": "Sample Rate",
            "disable_correlation": true,
            "misp-attribute": "text",
            "ui-priority": 0
        },
        "Vorbis-Title": {
            "description": "Title",
            "disable_correlation": true,
            "misp-attribute": "text",
            "ui-priority": 0
        },
        "Vorbis-TrackNumber": {
            "description": "Track Number",
            "disable_correlation": true,
            "misp-attribute": "text",
            "ui-priority": 0
        },
        "Vorbis-Vendor": {
            "description": "Vendor",
            "disable_correlation": true,
            "misp-attribute": "text",
            "ui-priority": 0
        },
        "Vorbis-VorbisVersion": {
            "description": "Vorbis Version",
            "disable_correlation": true,
            "misp-attribute": "text",
            "ui-priority": 0
        },
        "first-seen": {
            "disable_correlation": true,
            "misp-attribute": "datetime",
            "ui-priority": 0
        },
        "last-seen": {
            "disable_correlation": true,
            "misp-attribute": "datetime",
            "ui-priority": 0
        },
        "source-file": {
            "description": "Source filename",
            "disable_correlation": true,
            "misp-attribute": "filename",
            "ui-priority": 1
        }
    },
    "description": "Object describing file metadata.",
    "meta-category": "file",
    "name": "audio-ogg",
    "required": [
        "source-file"
    ],
    "uuid": "2671b41c-9a8a-4616-a6f6-2a0998aa29d2",
    "version": 1
}