{
  "attributes": {
    "ExifTool-ExifToolVersion": {
      "description": "ExifTool Version Number",
      "disable_correlation": true,
      "misp-attribute": "text",
      "ui-priority": 0
    },
    "File-Directory": {
      "description": "Directory",
      "disable_correlation": true,
      "misp-attribute": "text",
      "ui-priority": 0
    },
    "File-FileAccessDate": {
      "description": "File Access Date/Time",
      "disable_correlation": true,
      "misp-attribute": "datetime",
      "ui-priority": 0
    },
    "File-FileInodeChangeDate": {
      "description": "File Inode Change Date/Time",
      "disable_correlation": true,
      "misp-attribute": "datetime",
      "ui-priority": 0
    },
    "File-FileModifyDate": {
      "description": "File Modification Date/Time",
      "disable_correlation": true,
      "misp-attribute": "datetime",
      "ui-priority": 0
    },
    "File-FileName": {
      "description": "File Name",
      "disable_correlation": true,
      "misp-attribute": "text",
      "ui-priority": 0
    },
    "File-FilePermissions": {
      "description": "File Permissions",
      "disable_correlation": true,
      "misp-attribute": "text",
      "ui-priority": 0
    },
    "File-FileSize": {
      "description": "File Size",
      "disable_correlation": true,
      "misp-attribute": "text",
      "ui-priority": 0
    },
    "File-FileType": {
      "description": "File Type",
      "disable_correlation": true,
      "misp-attribute": "text",
      "ui-priority": 0
    },
    "File-FileTypeExtension": {
      "description": "File Type Extension",
      "disable_correlation": true,
      "misp-attribute": "text",
      "ui-priority": 0
    },
    "File-MIMEType": {
      "description": "MIME Type",
      "disable_correlation": true,
      "misp-attribute": "mime-type",
      "ui-priority": 0
    },
    "SourceFile": {
      "description": "Source File Path",
      "disable_correlation": true,
      "misp-attribute": "text",
      "ui-priority": 0
    },
    "ZIP-ArchivedFileName": {
      "description": "Archived File Name",
      "disable_correlation": true,
      "misp-attribute": "text",
      "ui-priority": 0
    },
    "ZIP-Comment": {
      "description": "Comment",
      "disable_correlation": true,
      "misp-attribute": "text",
      "ui-priority": 0
    },
    "ZIP-Compression": {
      "description": "Compression",
      "disable_correlation": true,
      "misp-attribute": "text",
      "ui-priority": 0
    },
    "ZIP-ExtraFlags": {
      "description": "Extra Flags",
      "disable_correlation": true,
      "misp-attribute": "text",
      "ui-priority": 0
    },
    "ZIP-Flags": {
      "description": "Flags",
      "disable_correlation": true,
      "misp-attribute": "text",
      "ui-priority": 0
    },
    "ZIP-ModifyDate": {
      "description": "Modify Date",
      "disable_correlation": true,
      "misp-attribute": "datetime",
      "ui-priority": 0
    },
    "ZIP-OperatingSystem": {
      "description": "Operating System",
      "disable_correlation": true,
      "misp-attribute": "text",
      "ui-priority": 0
    },
    "first-seen": {
      "description": "Source filename",
      "disable_correlation": true,
      "misp-attribute": "datetime",
      "ui-priority": 0
    },
    "last-seen": {
      "description": "Source filename",
      "disable_correlation": true,
      "misp-attribute": "datetime",
      "ui-priority": 0
    },
    "source-file": {
      "description": "Source filename",
      "disable_correlation": true,
      "misp-attribute": "filename",
      "ui-priority": 1
    }
  },
  "description": "Object describing file metadata.",
  "meta-category": "file",
  "name": "application-x-gzip",
  "required": [
    "source-file"
  ],
  "uuid": "caffd34a-f5c8-4f76-900b-12acaee2f1f4",
  "version": 1
}
